<?xml version="1.0" encoding="utf-8" ?>
<Defs>

	<!-- ======= Ingredient based thoughts ========= -->


	<ThoughtDef>	
		<defName>AC_ConsumedButter</defName>
		<thoughtClass>VanillaCookingExpanded.Thought_Hediff</thoughtClass>
		<hediff>AC_ConsumedButter</hediff>
		<durationDays>0.5</durationDays>
		<stages>
			<li>
				<label>consumed butter</label>
				<description>A taste so rich, it feels like a gentle hug for the soul.</description>
				<baseMoodEffect>1</baseMoodEffect>
			</li>
		</stages>	
		
	</ThoughtDef>

	
<ThoughtDef>	
		<defName>AC_ConsumedSourCream</defName>
		<thoughtClass>VanillaCookingExpanded.Thought_Hediff</thoughtClass>
		<hediff>AC_ConsumedSourCream</hediff>
		<durationDays>0.5</durationDays>
		<stages>
			<li>
				<label>consumed sour cream</label>
				<description>It's cool and tangy, like a little nudge to wake up the senses.</description>
				<baseMoodEffect>1</baseMoodEffect>
			</li>
		</stages>	
		
	</ThoughtDef>
	
	<ThoughtDef>	
		<defName>AC_ConsumedButtermilk</defName>
		<thoughtClass>VanillaCookingExpanded.Thought_Hediff</thoughtClass>
		<hediff>AC_ConsumedButtermilk</hediff>
		<durationDays>0.5</durationDays>
		<stages>
			<li>
				<label>consumed buttermilk</label>
				<description>A smooth, comforting flavor that feels like a connection to home.</description>
				<baseMoodEffect>1</baseMoodEffect>
			</li>
		</stages>	
		
	</ThoughtDef>

<ThoughtDef>	
		<defName>AC_ConsumedCondensedMilk</defName>
		<thoughtClass>VanillaCookingExpanded.Thought_Hediff</thoughtClass>
		<hediff>AC_ConsumedCondensedMilk</hediff>
		<durationDays>0.5</durationDays>
		<stages>
			<li>
				<label>consumed condensed milk</label>
				<description>Sweet and thick. It’s the kind of treat that lingers, in all the best ways.</description>
				<baseMoodEffect>2</baseMoodEffect>
			</li>
		</stages>	
		
	</ThoughtDef>

</Defs>
